PyPbitExtractor/Extractor.py
PyPbitExtractor/__init__.py
pypbitextractor-1.2.0.dist-info/METADATA
pypbitextractor-1.2.0.dist-info/WHEEL
pypbitextractor-1.2.0.dist-info/licenses/License.txt
pypbitextractor-1.2.0.dist-info/RECORD
