Metadata-Version: 2.1
Name: PyPbitExtractor
Version: 1.2.0
Summary: Extract Measures and its Description, Source Information, and Relationships from Power BI template.
Author-email: Akash Rajak <aakashrajak02@gmail.com>
Maintainer-email: Pragya Gautam <pragyagautam020801@gmail.com>, Akash Rajak <aakashrajak02@gmail.com>, Ayush Jain <jainaayush051@outlook.com>
License: MIT License
License-File: License.txt
Keywords: DAX Formatter,EXCEL,JSON,OpenAI,Power BI,pbit
Classifier: Development Status :: 3 - Alpha
Classifier: Intended Audience :: Developers
Classifier: License :: OSI Approved :: MIT License
Classifier: Programming Language :: Python :: 3
Classifier: Programming Language :: Python :: 3.7
Classifier: Programming Language :: Python :: 3.8
Classifier: Programming Language :: Python :: 3.9
Classifier: Programming Language :: Python :: 3.10
Classifier: Programming Language :: Python :: 3.11
Classifier: Topic :: Software Development :: Build Tools
Requires-Python: >=3.7
